asksageclient/__init__.py
asksageclient/client.py
asksageclient-1.42.dist-info/licenses/LICENSE
asksageclient-1.42.dist-info/METADATA
asksageclient-1.42.dist-info/WHEEL
asksageclient-1.42.dist-info/top_level.txt
asksageclient-1.42.dist-info/RECORD
