Metadata-Version: 2.4
Name: asksageclient
Version: 1.42
Summary: Ask Sage Python Client API
Author-email: "Ask Sage, Inc." <support@asksage.ai>
Project-URL: Homepage, https://github.com/Ask-Sage/asksage-client
Project-URL: Bug Tracker, https://github.com/Ask-Sage/asksage-client/issues
Classifier: Programming Language :: Python :: 3
Classifier: License :: Other/Proprietary License
Classifier: Operating System :: OS Independent
Requires-Python: >=3.7
License-File: LICENSE
Dynamic: license-file
